pynb_dag_runner_webui/__init__.py
pynb_dag_runner_webui-0.0.12.data/data/assets/asset-manifest.json
pynb_dag_runner_webui-0.0.12.data/data/assets/favicon.ico
pynb_dag_runner_webui-0.0.12.data/data/assets/index.html
pynb_dag_runner_webui-0.0.12.data/data/assets/manifest.json
pynb_dag_runner_webui-0.0.12.data/data/assets/pdf.worker.js
pynb_dag_runner_webui-0.0.12.data/data/assets/precache-manifest.3b71acb85a4068ea6f273db5d0aadbe1.js
pynb_dag_runner_webui-0.0.12.data/data/assets/service-worker.js
pynb_dag_runner_webui-0.0.12.data/data/assets/fontawesome/css/fontawesome-all.min.css
pynb_dag_runner_webui-0.0.12.data/data/assets/fontawesome/webfonts/fa-brands-400.eot
pynb_dag_runner_webui-0.0.12.data/data/assets/fontawesome/webfonts/fa-brands-400.svg
pynb_dag_runner_webui-0.0.12.data/data/assets/fontawesome/webfonts/fa-brands-400.ttf
pynb_dag_runner_webui-0.0.12.data/data/assets/fontawesome/webfonts/fa-brands-400.woff
pynb_dag_runner_webui-0.0.12.data/data/assets/fontawesome/webfonts/fa-brands-400.woff2
pynb_dag_runner_webui-0.0.12.data/data/assets/fontawesome/webfonts/fa-regular-400.eot
pynb_dag_runner_webui-0.0.12.data/data/assets/fontawesome/webfonts/fa-regular-400.svg
pynb_dag_runner_webui-0.0.12.data/data/assets/fontawesome/webfonts/fa-regular-400.ttf
pynb_dag_runner_webui-0.0.12.data/data/assets/fontawesome/webfonts/fa-regular-400.woff
pynb_dag_runner_webui-0.0.12.data/data/assets/fontawesome/webfonts/fa-regular-400.woff2
pynb_dag_runner_webui-0.0.12.data/data/assets/fontawesome/webfonts/fa-solid-900.eot
pynb_dag_runner_webui-0.0.12.data/data/assets/fontawesome/webfonts/fa-solid-900.svg
pynb_dag_runner_webui-0.0.12.data/data/assets/fontawesome/webfonts/fa-solid-900.ttf
pynb_dag_runner_webui-0.0.12.data/data/assets/fontawesome/webfonts/fa-solid-900.woff
pynb_dag_runner_webui-0.0.12.data/data/assets/fontawesome/webfonts/fa-solid-900.woff2
pynb_dag_runner_webui-0.0.12.data/data/assets/static/css/2.f78adf7b.chunk.css
pynb_dag_runner_webui-0.0.12.dist-info/METADATA
pynb_dag_runner_webui-0.0.12.dist-info/WHEEL
pynb_dag_runner_webui-0.0.12.dist-info/top_level.txt
pynb_dag_runner_webui-0.0.12.dist-info/RECORD
