Metadata-Version: 2.1
Name: pynb-dag-runner-webui
Version: 0.0.12
Summary: This Python package contain compiled web assets for a fork of the MLFlow front end.It is modified so that it can be deployed as a static website without a backend.
Home-page: https://pynb-dag-runner.github.io/pynb-dag-runner/
Author: Matias Dahl (based on a modified version of the MLFlow project)
Author-email: matias.dahl@iki.fi
License: Various, see the description
Platform: UNKNOWN
